configs/synth_paper.toml
src/omnitable.cpp
src/regression.cpp
src/fftarma.cpp
src/transform.cpp
src/resample.cpp
src/optimize.cpp
src/omniimg.cpp
src/omniinterface.cpp
tools/generate_version.py
tools/zenodo.py
tools/generate_requirements_txt.py
include/optimize/optimize.h
include/fftarma/fftarma.h
include/regression/regression.h
include/transform/transform.h
include/resample/resample.h
include/omniimg/omniimg.h
include/bsplineinterface/bsplineinterface.h
include/omnitable/omnitable.h
omnineuro-2023.2.1.dist-info/LICENSE
omnineuro-2023.2.1.dist-info/RECORD
omnineuro-2023.2.1.dist-info/entry_points.txt
omnineuro-2023.2.1.dist-info/METADATA
omnineuro-2023.2.1.dist-info/WHEEL
omnineuro-2023.2.1.dist-info/top_level.txt
docs/conf.py
docs/help.py
docs/arguments.py
omni_cpp/omni.cpython-38-x86_64-linux-gnu.so
omni_cpp/__init__.py
omni/path.py
omni/resample.py
omni/masks.py
omni/__init__.py
omni/affine.py
omni/register.py
omni/interface.py
omni/io.py
omni/preprocessing.py
omni/warp.py
omni/version.py
omni/scripts/extract.py
omni/scripts/info.py
omni/scripts/synthregressionmask.py
omni/scripts/pipeline.py
omni/scripts/preprocess.py
omni/scripts/resample.py
omni/scripts/fmap_correct.py
omni/scripts/intmat2nifti.py
omni/scripts/__init__.py
omni/scripts/affine.py
omni/scripts/docker.py
omni/scripts/synthpreproc.py
omni/scripts/synthnoisemask.py
omni/scripts/synthtarget.py
omni/scripts/deoblique.py
omni/scripts/realign4d.py
omni/scripts/warp.py
omni/scripts/synthunwarp.py
omni/scripts/common/__init__.py
omni/scripts/common/command.py
omni/scripts/common/help.py
omni/scripts/common/arguments.py
omni/interfaces/fsl.py
omni/interfaces/common.py
omni/interfaces/__init__.py
omni/interfaces/afni.py
omni/interfaces/ants.py
omni/pipelines/common.py
omni/pipelines/__init__.py
omni/pipelines/logging.py
omni/pipelines/bids.py
omni/pipelines/preprocessing.py
omni/pipelines/func/segmentation.py
omni/pipelines/func/masks.py
omni/pipelines/func/__init__.py
omni/pipelines/func/normalize.py
omni/pipelines/func/processing.py
omni/pipelines/func/align.py
omni/pipelines/func/stages.py
omni/pipelines/dwi/__init__.py
omni/pipelines/anat/segmentation.py
